lzqueue/__init__.py
lzqueue/base.py
lzqueue/cli.py
lzqueue/local_async.py
lzqueue/local_sync.py
lzqueue/sql.py
lzqueue/remote/__init__.py
lzqueue/remote/client.py
lzqueue/remote/models.py
lzqueue/remote/server.py
lzqueue-0.0.1.dist-info/LICENSE
lzqueue-0.0.1.dist-info/METADATA
lzqueue-0.0.1.dist-info/WHEEL
lzqueue-0.0.1.dist-info/entry_points.txt
lzqueue-0.0.1.dist-info/top_level.txt
lzqueue-0.0.1.dist-info/RECORD
