Metadata-Version: 2.2
Name: lzqueue
Version: 0.0.1
Summary: Lazy queue (lzqueue)
Author-email: Ian Maurer <imaurer@gmail.com>
Project-URL: Homepage, https://lzkit.com/lzqueue
Project-URL: Repository, https://github.com/lzkit/lzqueue
Project-URL: Documentation, https://lzkit.com/lzqueue
Keywords: python
Classifier: Intended Audience :: Developers
Classifier: Programming Language :: Python
Classifier: Programming Language :: Python :: 3
Classifier: Programming Language :: Python :: 3.10
Classifier: Programming Language :: Python :: 3.11
Classifier: Programming Language :: Python :: 3.12
Classifier: Programming Language :: Python :: 3.13
Classifier: Topic :: Software Development :: Libraries :: Python Modules
Requires-Python: <4.0,>=3.10
License-File: LICENSE
Requires-Dist: aiosqlite>=0.20.0
Requires-Dist: click>=8.1.8
Requires-Dist: pydantic>=2.10.5
Provides-Extra: api
Requires-Dist: fastapi>=0.115.6; extra == "api"
Requires-Dist: httpx>=0.28.1; extra == "api"
Requires-Dist: uvicorn>=0.34.0; extra == "api"
